streamlit_forum/__init__.py
streamlit_forum-0.0.1.dist-info/LICENSE
streamlit_forum-0.0.1.dist-info/METADATA
streamlit_forum-0.0.1.dist-info/WHEEL
streamlit_forum-0.0.1.dist-info/top_level.txt
streamlit_forum-0.0.1.dist-info/RECORD
